{
  "blocks remaining": "בלוקים שנותרו",
  "block remaining": "בלוק שנותר",
  "Waiting for your wallet approval": "ממתין לאישור מהארנק",
  "Processing transaction": "מעבד טרנזקציה",
  "Transaction successful": "טרנזקציה אושרה",
  "Redemption successful": "משיכה אושרה",
  "Transaction failed": "טרנזקציה נכשלה",
  "Processing FRAX approval": "אישור FRAX מעבד",
  "1st transaction successful. Waiting for your 2nd wallet approval": "טרנזקציה ראשונה אושרה. ממתין לאישור שני מהארנק",
  "FRAX allowance approved": "אושר FRAX תשלום",
  "Processing redemption": "מעבד בקשת משיכה",
  "Redemption initiated. Waiting for {{val1}} block{{val2}}": "{{val2}} בלוק {{val1}}-בקשת משיכה אותחלה. ממתין ל",
  "Redemption initiated": "בקשת משיכה אותחלה",
  "REDEEM": "פדיון",
  "COLLATERAL RATIO": "יחס הישענות",
  "REDEMPTION FEE": "עמלת פדיון",
  "POOL BALANCE": "יתרת פּוּל",
  "Insufficient Balance": "יתרה לא מספיקה",
  "Not enough free collateral in the pool!": "אין מספיק בטחונות חופשיים בפּוּל",
  "You must wait for at least {{val1}} block {{val2}} to be able to complete your redemption": "כדי שהשלמת הפדיון תתאפשר {{val2}} בלוק {{val1}} עליך להמתין לפחות",
  "Redeemable FXS": "FXS פנויים לפדיון",
  "Redeemable Collateral": "בטחונות פנויים לפדיון",
  "Redeem Initiated Block": "פדה את הבלוק שאותחל",
  "Redeem Claimable Block": "פדה את הבלוק החופשי",
  "Current Block": "בלוק נוכחי",
  "COLLECT": "אסוף",
  "WAIT TO COLLECT": "המתן לאיסוף"
}
