{
  "Waiting for your wallet approval": "Чекаємо на схвалення Вашого гаманця",
  "Processing FXS approval": "Оброблюємо схвалення FXS",
  "1st transaction successful. Waiting for your 2nd wallet approval": "1ша транзакція успішна. Чекаємо схвалення Вашого 2го гаманця",
  "FXS allowance approved": "Надбавку FXS схвалено",
  "Transaction failed": "Транзакція не успішна",
  "Processing buyback transaction": "Обробляємо зворотній викуп",
  "Buyback successful": "Зворотній викуп успішний",
  "Processing {{val}} approval": "Схвалення {{val}} обробки",
  "Collateral allowance approved": "Додаткову надбавку схвалено",
  "Processing recollateralization": "Обробка повторної застави",
  "Recollateralization successful": "Повторна застава успішна",
  "FRAX recollateralized": "FRAX отримав повторну заставу",
  "There is currently no excess value to conduct buybacks": "На даний момент немає надмірної вартості для проведення зворотнього викупу",
  "BUYBACK": "ВИКУПИТИ",
  "THEORETICALLY AVAILABLE": "THEORETICALLY AVAILABLE",
  "COLLATERAL RATIO": "КОЕФІЦІЄНТ ПОКРИТТЯ ЗАБЕЗПЕЧЕННЯ",
  "FXS Balance": "Баланс FXS",
  "Available for Buyback": "Доступно для зворотнього викупу",
  "EXCHANGE RATES": "ОБМІННІ КУРСИ",
  "SWAP FEE": "КОМІСІЯ КОНВЕРТАЦІЇ",
  "YOU RECEIVE": "ВИ ОТРИМУЄТЕ",
  "Recollaterization unavailable.": "Recollaterization unavailable.",
  "The protocol is properly collateralized.": "Протокол правильно забезпечений заставою.",
  "RECOLLATERALIZE": "ЗРОБИТИ ПОВТОРНУ ЗАСТАВУ",
  "BONUS RATE": "БОНУСНА СТАВКА",
  "Collateral Amount": "Сума застави",
  "Collateral Balance": "Баланс застави",
  "Recollateralization Available": "Доступна повторна застава"
}
