{
  "Price": "Ціна",
  "Supply": "Постачання",
  "Market Cap": "Ринкова капіталізація",
  "Circulating Supply": "Приблизна кількість токенів в обороті",
  "Circ. Market Cap": "Ринкова капіталізація в обороті",
  "FXS Burned": "Згоріли FXS",
  "Ratio": "Коефіцієнт",
  "Total Value (USD)": "Загальна вартість (USD)",
  "All Time": "Весь час",
  "1 Year": "1 рік",
  "6 Months": "6 місяців",
  "3 Months": "3 місяці",
  "1 Month": "1 місяць",
  "1 Week": "1 тиждень",
  "1 Day": "1 день",
  "8 Hours": "8 годин",
  "1 Hour": "1 година",
  "15 Minutes": "15 хвилин",
  "Total Value": "Загальна вартість",
  "Investments": "Інвестиції",
  "% Algorithmic": "% Алгоритмічний",
  "Algorithmic": "Алгоритмічний",
  "Free": "Комісія",
  "Collateralized": "Забезпечено заставою",
  "TOTAL VALUE": "ЗАГАЛЬНА ВАРТІСТЬ",
  "TOTAL INVESTED": "ВСЬОГО ІНВЕСТОВАНО",
  "ALGORITHMIC RATIO": "АЛГОРИТМІЧНИЙ КОЕФІЦІЄНТ",
  "PRICE": "ЦІНА",
  "From CoinGecko": "Від CoinGecko",
  "SUPPLY": "ПОСТАЧАННЯ",
  "MARKET CAP": "РИНКОВА КАПІТАЛІЗАЦІЯ",
  "COLLATERAL RATIO": "КОЕФІЦІЄНТ ПОКРИТТЯ ЗАБЕЗПЕЧЕННЯ",
  "GROWTH RATIO": "КОЕФІЦІЄНТ РОСТУ",
  "CIRC. SUPPLY": "ПОСТАЧАННЯ ТОКЕНІВ В ОБОРОТ",
  "Circulating Supply. Estimated from CoinGecko": "Постачання токенів в оборот. Оцінка від CoinGecko",
  "CIRC. MARKET CAP": "РИНКОВА КАПІТАЛІЗАЦІЯ В ОБОРОТІ",
  "Circulating Market Cap. Estimated from CoinGecko": "Постачання токенів в оборот. Оцінка від CoinGecko"
}
