{
  "blocks remaining": "blocos restantes",
  "block remaining": "bloco restante",
  "Waiting for your wallet approval": "A aguardar a sua aprovação de carteira",
  "Processing transaction": "A processar a transação",
  "Transaction successful": "Transação bem sucedida",
  "Redemption successful": "Resgate bem sucedido",
  "Transaction failed": "Transação mal sucedida",
  "Processing FRAX approval": "A processar aprovação de FRAX",
  "1st transaction successful. Waiting for your 2nd wallet approval": "1ª transação bem sucedida. À espera da sua 2ª aprovação de carteira",
  "FRAX allowance approved": "Subsídio de FRAX aprovado",
  "Processing redemption": "A processar resgate",
  "Redemption initiated. Waiting for {{val1}} block{{val2}}": "Resgate iniciado. à espera de {{val1}} bloco{{val2}}",
  "Redemption initiated": "Resgate iniciado",
  "REDEEM": "REDIMIR",
  "COLLATERAL RATIO": "RÁCIO DE GARANTIA",
  "REDEMPTION FEE": "TAXA DE RESGATE",
  "POOL BALANCE": "BALANÇO DA POOL",
  "Insufficient Balance": "Balanço insuficiente",
  "Not enough free collateral in the pool!": "Não há garantia gratuita suficiente na pool!",
  "You must wait for at least {{val1}} block {{val2}} to be able to complete your redemption": "Deve esperar pelo menos {{val1}} bloco {{val2}} para completar o seu resgate",
  "Redeemable FXS": "FXS Redimíveis",
  "Redeemable Collateral": "Garantía Redimível",
  "Redeem Initiated Block": "Redimir Iniciado Bloco",
  "Redeem Claimable Block": "Redimir Pedido Bloco",
  "Current Block": "Bloco Atual",
  "COLLECT": "RECOLHER",
  "WAIT TO COLLECT": "ESPERE PARA RECOLHER"

}
