{
  "Waiting for your wallet approval...": "Votre portefeuille est en attente d'approbation...",
  "Processing oracle update...": "Mise à jour de l’oracle...",
  "Oracle successfully updated...": "Mise à jour oracle réussie...",
  "Oracle update successful": "Mise à jour oracle réussie",
  "Transaction failed": "La transaction a échoué",
  "The FXS oracle is stale. All actions are frozen until it is updated.": "L’oracle FXS est périmé. Toutes les actions sont gelées jusqu'à ce qu'il soit mis à jour.",
  "Refresh Oracle": "Rafraîchir Oracle"
}
