{
  "Waiting for your wallet approval...": "Ожидание разрешения от вашего кошелька...",
  "Processing oracle update...": "Процесс обновления оракула...",
  "Oracle successfully updated...": "Оракул успешно обновлен...",
  "Oracle update successful": "Oракул обновлен успешно",
  "Transaction failed": "Транзакция не удалась",
  "The FXS oracle is stale. All actions are frozen until it is updated.": "Оракул FXS устарел. Все действия заморожены до его обновления.",
  "Refresh Oracle": "Обновить Оракул"
}
